README.md
pyproject.toml
setup.cfg
setup.py
request_digit_token/__init__.py
request_digit_token/_base.py
request_digit_token/_config.py
request_digit_token/_mailer.py
request_digit_token/_servlets.py
request_digit_token/_utils.py
request_digit_token/py.typed
synapse_request_digit_token.egg-info/PKG-INFO
synapse_request_digit_token.egg-info/SOURCES.txt
synapse_request_digit_token.egg-info/dependency_links.txt
synapse_request_digit_token.egg-info/requires.txt
synapse_request_digit_token.egg-info/top_level.txt