Metadata-Version: 2.1
Name: synapse-request-digit-token
Version: 1.0.0
Summary: A Campgrounds Synapse module that generates an n-digit verification code when signing up through email.
Classifier: License :: OSI Approved :: Apache Software License
Requires-Python: >=3.7
Provides-Extra: dev
